{
  "version": "7",
  "dialect": "postgresql",
  "entries": [
    {
      "idx": 0,
      "version": "7",
      "when": 1763406880019,
      "tag": "0000_flippant_luke_cage",
      "breakpoints": true
    },
    {
      "idx": 1,
      "version": "7",
      "when": 1763594511882,
      "tag": "0001_phase5b_inter_union_features",
      "breakpoints": true
    },
    {
      "idx": 2,
      "version": "7",
      "when": 1764959563791,
      "tag": "0002_true_selene",
      "breakpoints": true
    },
    {
      "idx": 3,
      "version": "7",
      "when": 1764959585710,
      "tag": "0003_curious_agent_zero",
      "breakpoints": true
    },
    {
      "idx": 4,
      "version": "7",
      "when": 1770355877546,
      "tag": "0004_phase2_complete",
      "breakpoints": true
    },
    {
      "idx": 5,
      "version": "7",
      "when": 1770371778360,
      "tag": "0005_lazy_kate_bishop",
      "breakpoints": true
    },
    {
      "idx": 6,
      "version": "7",
      "when": 1770537031000,
      "tag": "0006_flat_stepford_cuckoos",
      "breakpoints": true
    },
    {
      "idx": 7,
      "version": "7",
      "when": 1770621501496,
      "tag": "0007_add_wage_benchmarks",
      "breakpoints": true
    },
    {
      "idx": 8,
      "version": "7",
      "when": 1770880651726,
      "tag": "0008_lean_mother_askani",
      "breakpoints": true
    }
  ]
}